hkhklab
